README.md
setup.cfg
setup.py
django_ip_geolocation/__init__.py
django_ip_geolocation/decorators.py
django_ip_geolocation/middleware.py
django_ip_geolocation/settings.py
django_ip_geolocation/utils.py
django_ip_geolocation.egg-info/PKG-INFO
django_ip_geolocation.egg-info/SOURCES.txt
django_ip_geolocation.egg-info/dependency_links.txt
django_ip_geolocation.egg-info/requires.txt
django_ip_geolocation.egg-info/top_level.txt
django_ip_geolocation/backends/__init__.py
django_ip_geolocation/backends/base.py
django_ip_geolocation/backends/ip2locationcom.py
django_ip_geolocation/backends/ipgeolocationapi.py
django_ip_geolocation/backends/ipstack.py