Metadata-Version: 2.1
Name: django-ip-geolocation
Version: 1.4.1
Summary: Django request/response hook (Middleware and Decorator) to geolocate visitors using their IP address
Home-page: https://github.com/rednaks/django-ip-geolocation
Author: Skander Ben Mahmoud
Author-email: skander.bmahmoud@gmail.com
License: MIT
Platform: UNKNOWN
Classifier: Development Status :: 5 - Production/Stable
Classifier: Framework :: Django
Classifier: Intended Audience :: Developers
Classifier: License :: OSI Approved :: MIT License
Classifier: Operating System :: OS Independent
Classifier: Programming Language :: Python
Classifier: Programming Language :: Python :: 2.6
Classifier: Programming Language :: Python :: 2.7
Classifier: Programming Language :: Python :: 3
Classifier: Programming Language :: Python :: 3.3
Classifier: Programming Language :: Python :: 3.4
